LICENSE
README.md
setup.cfg
setup.py
src/new_syntax/__init__.py
src/new_syntax/__main__.py
src/new_syntax/cli.py
src/new_syntax/py.typed
src/new_syntax.egg-info/PKG-INFO
src/new_syntax.egg-info/SOURCES.txt
src/new_syntax.egg-info/dependency_links.txt
src/new_syntax.egg-info/entry_points.txt
src/new_syntax.egg-info/requires.txt
src/new_syntax.egg-info/top_level.txt